README
setup.py
basedata/__init__.py
basedata.egg-info/PKG-INFO
basedata.egg-info/SOURCES.txt
basedata.egg-info/dependency_links.txt
basedata.egg-info/top_level.txt