Metadata-Version: 1.1
Name: basedata
Version: 0.2
Summary: support library for basedata.org
Home-page: https://basedata.org
Author: bd
Author-email: code@basedata.org
License: GPL 3
Download-URL: https://basedata.org/code/python-basedata/
Platform: UNKNOWN
Classifier: Operating System :: OS Independent
Classifier: Programming Language :: Python
Classifier: Topic :: Software Development :: Libraries :: Python Modules
